aiomqtt/__init__.py
aiomqtt/client.py
aiomqtt/exceptions.py
aiomqtt/message.py
aiomqtt/py.typed
aiomqtt/topic.py
aiomqtt/types.py
aiomqtt-2.3.1.dist-info/METADATA
aiomqtt-2.3.1.dist-info/WHEEL
aiomqtt-2.3.1.dist-info/licenses/LICENSE
aiomqtt-2.3.1.dist-info/RECORD
