Metadata-Version: 2.4
Name: aiomqtt
Version: 2.3.1
Summary: The idiomatic asyncio MQTT client
Project-URL: source, https://github.com/empicano/aiomqtt
Project-URL: documentation, https://aiomqtt.bo3hm.com
Project-URL: issues, https://github.com/empicano/aiomqtt/issues
Author-email: Frederik Aalund <fpa@sbtinstruments.com>, Felix Böhm <f@bo3hm.com>, Jonathan Plasse <jonathan.plasse@live.fr>
License-File: LICENSE
Keywords: asyncio,internet-of-things,iot,mqtt,mqttv5,paho-mqtt
Classifier: Development Status :: 4 - Beta
Classifier: Intended Audience :: Developers
Classifier: License :: OSI Approved :: BSD License
Classifier: Operating System :: OS Independent
Requires-Python: <4.0,>=3.8
Requires-Dist: paho-mqtt<3.0.0,>=2.1.0
Requires-Dist: typing-extensions<5.0.0,>=4.4.0; python_version < '3.10'
